jrpyanalytics/__init__.py
jrpyanalytics/__version__.py
jrpyanalytics/datasets/__init__.py
jrpyanalytics/datasets/cars.py
jrpyanalytics/datasets/data/USArrests.zip
jrpyanalytics/datasets/data/cars.zip
jrpyanalytics/datasets/data/diabetes.zip
jrpyanalytics/datasets/diabetes.py
jrpyanalytics/datasets/usarrests.py
jrpyanalytics/vignettes/practical1.pdf
jrpyanalytics/vignettes/practical2.pdf
jrpyanalytics/vignettes/practical3.pdf
jrpyanalytics/vignettes/solutions1.pdf
jrpyanalytics/vignettes/solutions2.pdf
jrpyanalytics/vignettes/solutions3.pdf
jrpyanalytics/vignettes.py
jrpyanalytics-0.1.8.dist-info/WHEEL
jrpyanalytics-0.1.8.dist-info/METADATA
jrpyanalytics-0.1.8.dist-info/RECORD
